f_speak_heAR.py
example_pkg/__init__.py
f_speak_heAR-0.0.1.dist-info/LICENSE
f_speak_heAR-0.0.1.dist-info/METADATA
f_speak_heAR-0.0.1.dist-info/WHEEL
f_speak_heAR-0.0.1.dist-info/top_level.txt
f_speak_heAR-0.0.1.dist-info/RECORD
