Metadata-Version: 2.1
Name: f-speak-heAR
Version: 0.0.1
Summary: speak and take command functions
Home-page: https://github.com/Rohan-LK/f_speak_heAR.git
Author: Rohan Lal Kshetry
Author-email: rlkshetry95@gmail.com
License: UNKNOWN
Platform: UNKNOWN
Classifier: Programming Language :: Python :: 3
Classifier: License :: OSI Approved :: MIT License
Classifier: Operating System :: OS Independent
Requires-Python: >=3.0
